zktls/__init__.py
zktls/checks.py
zktls/node_wrapper.py
zktls_py_sdk-0.1.2.dist-info/METADATA
zktls_py_sdk-0.1.2.dist-info/WHEEL
zktls_py_sdk-0.1.2.dist-info/licenses/LICENSE
zktls_py_sdk-0.1.2.dist-info/RECORD
