Metadata-Version: 2.4
Name: zktls-py-sdk
Version: 0.1.2
Summary: A Python SDK for Primus Labs' Zero-Knowledge TLS (ZK TLS) protocol, enabling secure attestation and proxy TLS functionality for privacy-preserving data verification
Project-URL: Homepage, https://primuslabs.xyz
Project-URL: Repository, https://github.com/pkjha527/zktls-py-sdk.git
Project-URL: Documentation, https://github.com/pkjha527/zktls-py-sdk#readme
Project-URL: Bug Tracker, https://github.com/pkjha527/zktls-py-sdk/issues
Author-email: Praveen Kumar Jha <praveen@gamp.gg>
License-Expression: MIT
License-File: LICENSE
Keywords: attestation,blockchain,ethereum,privacy,tls,zero-knowledge,zk
Classifier: Development Status :: 4 - Beta
Classifier: Intended Audience :: Developers
Classifier: License :: OSI Approved :: MIT License
Classifier: Operating System :: OS Independent
Classifier: Programming Language :: Python :: 3
Classifier: Programming Language :: Python :: 3.8
Classifier: Programming Language :: Python :: 3.9
Classifier: Programming Language :: Python :: 3.10
Classifier: Programming Language :: Python :: 3.11
Classifier: Topic :: Security :: Cryptography
Classifier: Topic :: Software Development :: Libraries :: Python Modules
Requires-Python: >=3.8
Requires-Dist: aiohttp>=3.8.0
Requires-Dist: asyncio>=3.4.3
Requires-Dist: eth-account>=0.8.0
Requires-Dist: eth-typing>=3.0.0
Requires-Dist: pydantic>=2.0.0
Requires-Dist: web3>=6.0.0
Provides-Extra: dev
Requires-Dist: black>=22.0.0; extra == 'dev'
Requires-Dist: flake8>=4.0.0; extra == 'dev'
Requires-Dist: isort>=5.10.0; extra == 'dev'
Requires-Dist: mypy>=0.900; extra == 'dev'
Requires-Dist: pylint>=2.12.0; extra == 'dev'
Provides-Extra: docs
Requires-Dist: myst-parser>=0.18.0; extra == 'docs'
Requires-Dist: sphinx-rtd-theme>=1.0.0; extra == 'docs'
Requires-Dist: sphinx>=4.0.0; extra == 'docs'
Provides-Extra: test
Requires-Dist: pytest-asyncio>=0.18.0; extra == 'test'
Requires-Dist: pytest-cov>=3.0.0; extra == 'test'
Requires-Dist: pytest-mock>=3.6.0; extra == 'test'
Requires-Dist: pytest>=7.0.0; extra == 'test'
